setup.py
frasco_invoicing/__init__.py
frasco_invoicing.egg-info/PKG-INFO
frasco_invoicing.egg-info/SOURCES.txt
frasco_invoicing.egg-info/dependency_links.txt
frasco_invoicing.egg-info/not-zip-safe
frasco_invoicing.egg-info/requires.txt
frasco_invoicing.egg-info/top_level.txt
frasco_invoicing/emails/invoice.html