Metadata-Version: 1.0
Name: frasco-invoicing
Version: 0.2.3
Summary: Invoicing for Frasco
Home-page: http://github.com/frascoweb/frasco-invoicing
Author: Maxime Bouroumeau-Fuseau
Author-email: maxime.bouroumeau@gmail.com
License: MIT
Platform: any
